LICENSE.txt
README.md
setup.py
netomaton/__init__.py
netomaton/analysis.py
netomaton/asynchronous_rule.py
netomaton/ctrbl_rule.py
netomaton/evolution.py
netomaton/fungal_growth_model.py
netomaton/hexplot.py
netomaton/hopfield_net.py
netomaton/hopfield_tank_tsp_net.py
netomaton/langtons_loop.py
netomaton/reversible_rule.py
netomaton/rule_tables.py
netomaton/sandpile.py
netomaton/state.py
netomaton/substitution_system.py
netomaton/turing_machine.py
netomaton/turtle.py
netomaton/utils.py
netomaton/wolfram_physics_model.py
netomaton.egg-info/PKG-INFO
netomaton.egg-info/SOURCES.txt
netomaton.egg-info/dependency_links.txt
netomaton.egg-info/requires.txt
netomaton.egg-info/top_level.txt
netomaton/rules/__init__.py
netomaton/rules/activity_rule.py
netomaton/topology/__init__.py
netomaton/topology/adjacency.py
netomaton/topology/networks.py
netomaton/vis/__init__.py
netomaton/vis/vis_utils.py