Metadata-Version: 2.1
Name: netomaton
Version: 1.3.0
Summary: Netomaton, A Python library for working with Network Automata.
Home-page: http://github.com/lantunes/netomaton
Author: Luis M. Antunes
Author-email: lantunes@gmail.com
License: Apache License 2.0
Keywords: network automata,cellular automata,complexity,complex systems,computation,non-linear dynamics
Platform: UNKNOWN
Classifier: Development Status :: 5 - Production/Stable
Classifier: Intended Audience :: Developers
Classifier: Topic :: Scientific/Engineering :: Artificial Intelligence
Classifier: License :: OSI Approved :: Apache Software License
Classifier: Programming Language :: Python :: 3.5
Classifier: Programming Language :: Python :: 3.6
Requires-Python: >3.5.2
License-File: LICENSE.txt
